megatron/core/README.md
megatron/core/__init__.py
megatron/core/activations.py
megatron/core/config.py
megatron/core/config_logger.py
megatron/core/energy_monitor.py
megatron/core/enums.py
megatron/core/fp4_utils.py
megatron/core/fp8_utils.py
megatron/core/full_cuda_graph.py
megatron/core/hyper_comm_grid.py
megatron/core/inference_params.py
megatron/core/jit.py
megatron/core/model_parallel_config.py
megatron/core/msc_utils.py
megatron/core/nccl_allocator.py
megatron/core/num_microbatches_calculator.py
megatron/core/optimizer_param_scheduler.py
megatron/core/package_info.py
megatron/core/packed_seq_params.py
megatron/core/parallel_state.py
megatron/core/process_groups_config.py
megatron/core/requirements.txt
megatron/core/rerun_state_machine.py
megatron/core/safe_globals.py
megatron/core/timers.py
megatron/core/utils.py
megatron/core/datasets/__init__.py
megatron/core/datasets/bert_dataset.py
megatron/core/datasets/blended_dataset.py
megatron/core/datasets/blended_megatron_dataset_builder.py
megatron/core/datasets/blended_megatron_dataset_config.py
megatron/core/datasets/gpt_dataset.py
megatron/core/datasets/helpers.cpp
megatron/core/datasets/helpers.py
megatron/core/datasets/helpers_cpp.cpython-312-x86_64-linux-gnu.so
megatron/core/datasets/indexed_dataset.py
megatron/core/datasets/masked_dataset.py
megatron/core/datasets/megatron_dataset.py
megatron/core/datasets/megatron_tokenizer.py
megatron/core/datasets/multimodal_dataset.py
megatron/core/datasets/object_storage_utils.py
megatron/core/datasets/t5_dataset.py
megatron/core/datasets/utils.py
megatron/core/datasets/utils_object_storage.py
megatron/core/datasets/utils_s3.py
megatron/core/datasets/retro/__init__.py
megatron/core/datasets/retro/external_libs.py
megatron/core/datasets/retro/utils.py
megatron/core/datasets/retro/config/__init__.py
megatron/core/datasets/retro/config/bert_embedders.py
megatron/core/datasets/retro/config/config.py
megatron_core-0.15.2.dist-info/METADATA
megatron_core-0.15.2.dist-info/WHEEL
megatron_core-0.15.2.dist-info/top_level.txt
megatron_core-0.15.2.dist-info/RECORD
