Metadata-Version: 2.4
Name: megatron-core
Version: 0.15.2
Summary: Megatron Core - a library for efficient and scalable training of transformer based models
Author-email: NVIDIA <nemo-toolkit@nvidia.com>
Maintainer-email: NVIDIA <nemo-toolkit@nvidia.com>
License: Apache 2.0
Project-URL: Download, https://github.com/NVIDIA/Megatron-LM/releases
Project-URL: Homepage, https://github.com/NVIDIA/Megatron-LM/megatron/core
Keywords: NLP,NLU,deep,gpu,language,learning,learning,machine,nvidia,pytorch,torch,transformer
Classifier: Development Status :: 5 - Production/Stable
Classifier: Environment :: Console
Classifier: Intended Audience :: Developers
Classifier: Intended Audience :: Information Technology
Classifier: Intended Audience :: Science/Research
Classifier: License :: OSI Approved :: BSD License
Classifier: Natural Language :: English
Classifier: Operating System :: OS Independent
Classifier: Programming Language :: Python :: 3
Classifier: Programming Language :: Python :: 3.10
Classifier: Programming Language :: Python :: 3.11
Classifier: Programming Language :: Python :: 3.12
Classifier: Topic :: Scientific/Engineering :: Artificial Intelligence
Classifier: Topic :: Scientific/Engineering :: Image Recognition
Classifier: Topic :: Scientific/Engineering :: Mathematics
Classifier: Topic :: Scientific/Engineering
Classifier: Topic :: Software Development :: Libraries :: Python Modules
Classifier: Topic :: Software Development :: Libraries
Classifier: Topic :: Utilities
Requires-Python: >=3.10
Requires-Dist: torch
Requires-Dist: numpy<2.0.0
Requires-Dist: packaging>=24.2
Provides-Extra: mlm
Requires-Dist: flask-restful; extra == "mlm"
Requires-Dist: sentencepiece; extra == "mlm"
Requires-Dist: tiktoken; extra == "mlm"
Requires-Dist: wandb; extra == "mlm"
Requires-Dist: transformers; extra == "mlm"
Provides-Extra: dev
Requires-Dist: nvidia-modelopt[torch]; sys_platform != "darwin" and extra == "dev"
Requires-Dist: transformer-engine[pytorch]<2.10.0,>=2.9.0a0; extra == "dev"
Requires-Dist: nvidia-resiliency-ext<0.5.0,>=0.4.0a0; extra == "dev"
Requires-Dist: tqdm; extra == "dev"
Requires-Dist: einops~=0.8; extra == "dev"
Requires-Dist: tensorstore!=0.1.46,!=0.1.72,~=0.1; extra == "dev"
Requires-Dist: nvtx~=0.2; extra == "dev"
Requires-Dist: multi-storage-client~=0.27; extra == "dev"
Requires-Dist: opentelemetry-api~=1.33.1; extra == "dev"
Requires-Dist: setuptools<80.0.0; extra == "dev"
Requires-Dist: mamba-ssm~=2.2; extra == "dev"
Requires-Dist: causal-conv1d~=1.5; extra == "dev"
Requires-Dist: nv-grouped-gemm~=1.1; extra == "dev"
Requires-Dist: megatron-energon[av_decode]~=6.0; extra == "dev"
Requires-Dist: av<16.0.0; extra == "dev"
Requires-Dist: flashinfer-python; extra == "dev"
Requires-Dist: wget; extra == "dev"
Requires-Dist: onnxscript; extra == "dev"
Provides-Extra: lts
Requires-Dist: tqdm; extra == "lts"
Requires-Dist: einops; extra == "lts"
Requires-Dist: tensorstore!=0.1.46,!=0.1.72; extra == "lts"
Requires-Dist: nvtx; extra == "lts"
Requires-Dist: transformers; extra == "lts"
Requires-Dist: zarr; extra == "lts"
Requires-Dist: setuptools<80.0.0; extra == "lts"
Requires-Dist: wget; extra == "lts"
